{
  "studentRaport": {
    "resultValue": {
      "scos": [],
      "trainingId": 7,
      "student": "Grzegorz B",
      "course": "ITS CaseStudy: Mentalities and perspectives in archaeological heritage management",
      "training": "WeryfikacjaKursów"
    },
    "errorCode": 0,
    "errorInfo": "OK"
  },
  "teacherRecommendation": {
    "resultValue": {
      "studentId": 478,
      "trainingId": 7,
      "student": "Grzegorz B",
      "course": "ITS CaseStudy: Mentalities and perspectives in archaeological heritage management",
      "training": "WeryfikacjaKursów",
      "studentLogin": "grzegorz",
      "itsHistory": [
        {
          "otherProposals": [
            {
              "scoreInfo": "Testowa informacja testowego ITS-aTestowa informacja testowego ITS-a",
              "score": "2320.10",
              "proposalCreationDate": "2018-04-26 11:20:12",
              "beforeOrAfter": "after",
              "removeOrAdd": "add",
              "proposalForItem": {
                "identifier": "edumatic_ITS1263",
                "id": 2671,
                "type": "sco"
              },
              "proposedItem": {
                "identifier": "modul_10_part03_EN_1_0org",
                "children": [
                  {
                    "identifier": "modul_10_part03_title",
                    "id": 823,
                    "type": "sco"
                  },
                  {
                    "identifier": "s101e7816892-e1d4-4a84-be80-005c9a47f6b5",
                    "id": 824,
                    "type": "sco"
                  },
                  {
                    "identifier": "s102e7816892-e1d4-4a84-be80-005c9a47f6b5",
                    "id": 825,
                    "type": "sco"
                  },
                  {
                    "identifier": "s103e7816892-e1d4-4a84-be80-005c9a47f6b5",
                    "id": 826,
                    "type": "sco"
                  },
                  {
                    "identifier": "s104e7816892-e1d4-4a84-be80-005c9a47f6b5",
                    "id": 827,
                    "type": "sco"
                  },
                  {
                    "identifier": "s105e7816892-e1d4-4a84-be80-005c9a47f6b5",
                    "id": 828,
                    "type": "sco"
                  }
                ],
                "id": 313,
                "type": "block"
              },
              "proposalId": 113
            },
            {
              "scoreInfo": "Testowa informacja testowego ITS-aTestowa informacja testowego ITS-a",
              "score": "2320.30",
              "proposalCreationDate": "2018-04-26 11:20:12",
              "beforeOrAfter": "after",
              "removeOrAdd": "add",
              "proposalForItem": {
                "identifier": "edumatic_ITS1263",
                "id": 2671,
                "type": "sco"
              },
              "proposedItem": {
                "identifier": "modul_02_part02_01_EN_1_0org",
                "children": [
                  {
                    "identifier": "modul_2_lu_2_1_title",
                    "id": 853,
                    "type": "sco"
                  },
                  {
                    "identifier": "s1016ba9df89-3ad2-4871-b090-334432913f40",
                    "id": 854,
                    "type": "sco"
                  },
                  {
                    "identifier": "s1026ba9df89-3ad2-4871-b090-334432913f40",
                    "id": 855,
                    "type": "sco"
                  },
                  {
                    "identifier": "s1036ba9df89-3ad2-4871-b090-334432913f40",
                    "id": 856,
                    "type": "sco"
                  },
                  {
                    "identifier": "s1046ba9df89-3ad2-4871-b090-334432913f40",
                    "id": 857,
                    "type": "sco"
                  },
                  {
                    "identifier": "s1056ba9df89-3ad2-4871-b090-334432913f40",
                    "id": 858,
                    "type": "sco"
                  },
                  {
                    "identifier": "s1066ba9df89-3ad2-4871-b090-334432913f40",
                    "id": 859,
                    "type": "sco"
                  },
                  {
                    "identifier": "s1076ba9df89-3ad2-4871-b090-334432913f40",
                    "id": 860,
                    "type": "sco"
                  },
                  {
                    "identifier": "s1086ba9df89-3ad2-4871-b090-334432913f40",
                    "id": 861,
                    "type": "sco"
                  }
                ],
                "id": 318,
                "type": "block"
              },
              "proposalId": 109
            },
            {
              "scoreInfo": "Testowa informacja testowego ITS-aTestowa informacja testowego ITS-a",
              "score": "2320.30",
              "proposalCreationDate": "2018-04-26 11:20:12",
              "beforeOrAfter": "after",
              "removeOrAdd": "add",
              "proposalForItem": {
                "identifier": "edumatic_ITS1263",
                "id": 2671,
                "type": "sco"
              },
              "proposedItem": {
                "identifier": "modul_04_part01_01_EN_1_0",
                "children": [
                  {
                    "identifier": "modul_04_lu_1_1_title",
                    "id": 561,
                    "type": "sco"
                  },
                  {
                    "identifier": "s101a3d3c595-47d9-4854-b36e-8eb60b9b85a4",
                    "id": 562,
                    "type": "sco"
                  },
                  {
                    "identifier": "s102a3d3c595-47d9-4854-b36e-8eb60b9b85a4",
                    "id": 563,
                    "type": "sco"
                  },
                  {
                    "identifier": "s103a3d3c595-47d9-4854-b36e-8eb60b9b85a4",
                    "id": 564,
                    "type": "sco"
                  },
                  {
                    "identifier": "s104a3d3c595-47d9-4854-b36e-8eb60b9b85a4",
                    "id": 565,
                    "type": "sco"
                  },
                  {
                    "identifier": "s105a3d3c595-47d9-4854-b36e-8eb60b9b85a4",
                    "id": 566,
                    "type": "sco"
                  },
                  {
                    "identifier": "s106a3d3c595-47d9-4854-b36e-8eb60b9b85a4",
                    "id": 567,
                    "type": "sco"
                  },
                  {
                    "identifier": "s107a3d3c595-47d9-4854-b36e-8eb60b9b85a4",
                    "id": 568,
                    "type": "sco"
                  }
                ],
                "id": 267,
                "type": "block"
              },
              "proposalId": 111
            },
            {
              "scoreInfo": "Testowa informacja testowego ITS-aTestowa informacja testowego ITS-a",
              "score": "2320.30",
              "proposalCreationDate": "2018-04-26 11:20:11",
              "beforeOrAfter": "after",
              "removeOrAdd": "add",
              "proposalForItem": {
                "identifier": "edumatic_ITS1263",
                "id": 2671,
                "type": "sco"
              },
              "proposedItem": {
                "identifier": "modul_04_part01_01_EN_1_0org",
                "children": [
                  {
                    "identifier": "modul_04_lu_1_1_title",
                    "id": 881,
                    "type": "sco"
                  },
                  {
                    "identifier": "s101a3d3c595-47d9-4854-b36e-8eb60b9b85a4",
                    "id": 882,
                    "type": "sco"
                  },
                  {
                    "identifier": "s102a3d3c595-47d9-4854-b36e-8eb60b9b85a4",
                    "id": 883,
                    "type": "sco"
                  },
                  {
                    "identifier": "s103a3d3c595-47d9-4854-b36e-8eb60b9b85a4",
                    "id": 884,
                    "type": "sco"
                  },
                  {
                    "identifier": "s104a3d3c595-47d9-4854-b36e-8eb60b9b85a4",
                    "id": 885,
                    "type": "sco"
                  },
                  {
                    "identifier": "s105a3d3c595-47d9-4854-b36e-8eb60b9b85a4",
                    "id": 886,
                    "type": "sco"
                  },
                  {
                    "identifier": "s106a3d3c595-47d9-4854-b36e-8eb60b9b85a4",
                    "id": 887,
                    "type": "sco"
                  },
                  {
                    "identifier": "s107a3d3c595-47d9-4854-b36e-8eb60b9b85a4",
                    "id": 888,
                    "type": "sco"
                  }
                ],
                "id": 322,
                "type": "block"
              },
              "proposalId": 108
            }
          ],
          "reviewProposal:": {
            "scoreInfo": "Testowa informacja testowego ITS-aTestowa informacja testowego ITS-a",
            "score": "2320.10",
            "proposalCreationDate": "2018-04-26 11:20:12",
            "beforeOrAfter": "after",
            "removeOrAdd": "add",
            "proposalForItem": {
              "identifier": "edumatic_ITS1263",
              "id": 2671,
              "type": "sco"
            },
            "proposedItem": {
              "identifier": "modul_11_part02_EN_1_0org",
              "children": [
                {
                  "identifier": "modul_11_part02_title",
                  "id": 815,
                  "type": "sco"
                },
                {
                  "identifier": "s101def9233b-9941-4c25-b220-4ca69c29d9e4",
                  "id": 816,
                  "type": "sco"
                },
                {
                  "identifier": "s102def9233b-9941-4c25-b220-4ca69c29d9e4",
                  "id": 817,
                  "type": "sco"
                },
                {
                  "identifier": "s103def9233b-9941-4c25-b220-4ca69c29d9e4",
                  "id": 818,
                  "type": "sco"
                },
                {
                  "identifier": "s104def9233b-9941-4c25-b220-4ca69c29d9e4",
                  "id": 819,
                  "type": "sco"
                },
                {
                  "identifier": "s105def9233b-9941-4c25-b220-4ca69c29d9e4",
                  "id": 820,
                  "type": "sco"
                },
                {
                  "identifier": "s106def9233b-9941-4c25-b220-4ca69c29d9e4",
                  "id": 821,
                  "type": "sco"
                },
                {
                  "identifier": "s107def9233b-9941-4c25-b220-4ca69c29d9e4",
                  "id": 822,
                  "type": "sco"
                }
              ],
              "id": 312,
              "type": "block"
            },
            "proposalId": 112
          },
          "reviewDate": "2018-07-19 17:05:14",
          "reviewAction": "approved"
        },
        {
          "otherProposals": [
            {
              "scoreInfo": "Testowa informacja testowego ITS-aTestowa informacja testowego ITS-a",
              "score": "2320.10",
              "proposalCreationDate": "2018-04-26 11:20:12",
              "beforeOrAfter": "after",
              "removeOrAdd": "add",
              "proposalForItem": {
                "identifier": "edumatic_ITS1263",
                "id": 2671,
                "type": "sco"
              },
              "proposedItem": {
                "identifier": "modul_10_part03_EN_1_0org",
                "children": [
                  {
                    "identifier": "modul_10_part03_title",
                    "id": 823,
                    "type": "sco"
                  },
                  {
                    "identifier": "s101e7816892-e1d4-4a84-be80-005c9a47f6b5",
                    "id": 824,
                    "type": "sco"
                  },
                  {
                    "identifier": "s102e7816892-e1d4-4a84-be80-005c9a47f6b5",
                    "id": 825,
                    "type": "sco"
                  },
                  {
                    "identifier": "s103e7816892-e1d4-4a84-be80-005c9a47f6b5",
                    "id": 826,
                    "type": "sco"
                  },
                  {
                    "identifier": "s104e7816892-e1d4-4a84-be80-005c9a47f6b5",
                    "id": 827,
                    "type": "sco"
                  },
                  {
                    "identifier": "s105e7816892-e1d4-4a84-be80-005c9a47f6b5",
                    "id": 828,
                    "type": "sco"
                  }
                ],
                "id": 313,
                "type": "block"
              },
              "proposalId": 113
            },
            {
              "scoreInfo": "Testowa informacja testowego ITS-aTestowa informacja testowego ITS-a",
              "score": "2320.30",
              "proposalCreationDate": "2018-04-26 11:20:12",
              "beforeOrAfter": "after",
              "removeOrAdd": "add",
              "proposalForItem": {
                "identifier": "edumatic_ITS1263",
                "id": 2671,
                "type": "sco"
              },
              "proposedItem": {
                "identifier": "modul_02_part02_01_EN_1_0org",
                "children": [
                  {
                    "identifier": "modul_2_lu_2_1_title",
                    "id": 853,
                    "type": "sco"
                  },
                  {
                    "identifier": "s1016ba9df89-3ad2-4871-b090-334432913f40",
                    "id": 854,
                    "type": "sco"
                  },
                  {
                    "identifier": "s1026ba9df89-3ad2-4871-b090-334432913f40",
                    "id": 855,
                    "type": "sco"
                  },
                  {
                    "identifier": "s1036ba9df89-3ad2-4871-b090-334432913f40",
                    "id": 856,
                    "type": "sco"
                  },
                  {
                    "identifier": "s1046ba9df89-3ad2-4871-b090-334432913f40",
                    "id": 857,
                    "type": "sco"
                  },
                  {
                    "identifier": "s1056ba9df89-3ad2-4871-b090-334432913f40",
                    "id": 858,
                    "type": "sco"
                  },
                  {
                    "identifier": "s1066ba9df89-3ad2-4871-b090-334432913f40",
                    "id": 859,
                    "type": "sco"
                  },
                  {
                    "identifier": "s1076ba9df89-3ad2-4871-b090-334432913f40",
                    "id": 860,
                    "type": "sco"
                  },
                  {
                    "identifier": "s1086ba9df89-3ad2-4871-b090-334432913f40",
                    "id": 861,
                    "type": "sco"
                  }
                ],
                "id": 318,
                "type": "block"
              },
              "proposalId": 109
            },
            {
              "scoreInfo": "Testowa informacja testowego ITS-aTestowa informacja testowego ITS-a",
              "score": "2320.30",
              "proposalCreationDate": "2018-04-26 11:20:11",
              "beforeOrAfter": "after",
              "removeOrAdd": "add",
              "proposalForItem": {
                "identifier": "edumatic_ITS1263",
                "id": 2671,
                "type": "sco"
              },
              "proposedItem": {
                "identifier": "modul_04_part01_01_EN_1_0org",
                "children": [
                  {
                    "identifier": "modul_04_lu_1_1_title",
                    "id": 881,
                    "type": "sco"
                  },
                  {
                    "identifier": "s101a3d3c595-47d9-4854-b36e-8eb60b9b85a4",
                    "id": 882,
                    "type": "sco"
                  },
                  {
                    "identifier": "s102a3d3c595-47d9-4854-b36e-8eb60b9b85a4",
                    "id": 883,
                    "type": "sco"
                  },
                  {
                    "identifier": "s103a3d3c595-47d9-4854-b36e-8eb60b9b85a4",
                    "id": 884,
                    "type": "sco"
                  },
                  {
                    "identifier": "s104a3d3c595-47d9-4854-b36e-8eb60b9b85a4",
                    "id": 885,
                    "type": "sco"
                  },
                  {
                    "identifier": "s105a3d3c595-47d9-4854-b36e-8eb60b9b85a4",
                    "id": 886,
                    "type": "sco"
                  },
                  {
                    "identifier": "s106a3d3c595-47d9-4854-b36e-8eb60b9b85a4",
                    "id": 887,
                    "type": "sco"
                  },
                  {
                    "identifier": "s107a3d3c595-47d9-4854-b36e-8eb60b9b85a4",
                    "id": 888,
                    "type": "sco"
                  }
                ],
                "id": 322,
                "type": "block"
              },
              "proposalId": 108
            }
          ],
          "reviewProposal:": {
            "scoreInfo": "Testowa informacja testowego ITS-aTestowa informacja testowego ITS-a",
            "score": "2320.30",
            "proposalCreationDate": "2018-04-26 11:20:12",
            "beforeOrAfter": "after",
            "removeOrAdd": "add",
            "proposalForItem": {
              "identifier": "edumatic_ITS1263",
              "id": 2671,
              "type": "sco"
            },
            "proposedItem": {
              "identifier": "modul_04_part01_01_EN_1_0",
              "children": [
                {
                  "identifier": "modul_04_lu_1_1_title",
                  "id": 561,
                  "type": "sco"
                },
                {
                  "identifier": "s101a3d3c595-47d9-4854-b36e-8eb60b9b85a4",
                  "id": 562,
                  "type": "sco"
                },
                {
                  "identifier": "s102a3d3c595-47d9-4854-b36e-8eb60b9b85a4",
                  "id": 563,
                  "type": "sco"
                },
                {
                  "identifier": "s103a3d3c595-47d9-4854-b36e-8eb60b9b85a4",
                  "id": 564,
                  "type": "sco"
                },
                {
                  "identifier": "s104a3d3c595-47d9-4854-b36e-8eb60b9b85a4",
                  "id": 565,
                  "type": "sco"
                },
                {
                  "identifier": "s105a3d3c595-47d9-4854-b36e-8eb60b9b85a4",
                  "id": 566,
                  "type": "sco"
                },
                {
                  "identifier": "s106a3d3c595-47d9-4854-b36e-8eb60b9b85a4",
                  "id": 567,
                  "type": "sco"
                },
                {
                  "identifier": "s107a3d3c595-47d9-4854-b36e-8eb60b9b85a4",
                  "id": 568,
                  "type": "sco"
                }
              ],
              "id": 267,
              "type": "block"
            },
            "proposalId": 111
          },
          "reviewDate": "2018-07-19 17:05:23",
          "reviewAction": "rejected"
        }
      ]
    },
    "errorCode": 0,
    "errorInfo": "OK"
  },
  "allStudentsRaport": {
    "resultValue": {
      "trainingId": 7,
      "course": "ITS CaseStudy: Mentalities and perspectives in archaeological heritage management",
      "students": [
        {
          "studentId": 478,
          "scos": [],
          "student": "Grzegorz B",
          "studentLogin": "grzegorz"
        }
      ],
      "training": "WeryfikacjaKursów"
    },
    "errorCode": 0,
    "errorInfo": "OK"
  }
}